utils4cpp/__init__.py
utils4cpp/constants.py
utils4cpp/flask.py
utils4cpp/models.py
utils4cpp/utils.py
utils4cpp-0.0.41.dist-info/LICENSE
utils4cpp-0.0.41.dist-info/METADATA
utils4cpp-0.0.41.dist-info/WHEEL
utils4cpp-0.0.41.dist-info/top_level.txt
utils4cpp-0.0.41.dist-info/RECORD
